src/main/rom.v
`timescale 1ps/1ps
//アドレスに対応した命令を出力する
module rom (ad, do);

	input [3:0] ad;
    output[7:0] do;

	reg [7:0] do;
        
	always @ (ad) begin
	    case(ad)
            //アドレス        ８ビットの１６進数命令
              4'b0000:  do <= #1 8'h0A; //ADD A, Im(1010)
              4'b0001:  do <= #1 8'h51; //ADD B, Im(0001)
              4'b0010:  do <= #1 8'h30; //MOV A, B
              4'b0011:  do <= #1 8'h70; //MOV B, A
              4'b0100:  do <= #1 8'h15; //MOV A, Im(0101)
              4'b0101:  do <= #1 8'h47; //MOV B, Im(0111)
              4'b0110:  do <= #1 8'hFF; //JMP Im(1111)
              4'b0111:  do <= #1 8'h00; //MOP
              4'b1111:  do <= #1 8'h0B; //ADD A, Im(1011)
              default:  do <= #1 8'h00; //NOP
        endcase
    end
endmodule

src/main/select.v
module selector (in1, in2, sel, out);
	input [3:0] in1, in2;
	input sel;
	output [3:0] out;
	reg [3:0] out;
		always @ (in1 or in2 or sel) begin
			if(sel == 0)begin
				out <= in1;
			end
			else begin
				out <= in2;
			end
		end
endmodule

src/main/adder.v
module adder (in1, in2, out);
   input[3:0]in1, in2;
   output[3:0]out;
   
   reg [3:0] out;

   always @ (in1 or in2) begin
	   out <= in1 + in2;
   end

endmodule

src/main/counter.v
`timescale 1ps/1ps
module counter (rst, clk, in, out);
   input rst,clk;
   input[3:0]in;
   output[3:0]out;
   reg[3:0]out;

   always @ (negedge rst or posedge clk) begin
      if(rst == 0) begin
         out <= 4'b0000;
      end
      else begin
         out <= in;
      end
   end

endmodule

src/main/fetch.v
`include "counter.v"
`include "rom.v"
`include "adder.v"
`include "select.v"

module fetch (rst, clk, jumpadrs, isjump, inst);
	input rst, clk, isjump;
    input[3:0] jumpadrs;
	output[7:0]inst;
	wire[3:0]pcout, nxtadrs, selout;

	counter i0 (.rst(rst), .clk(clk), .in(selout), .out(pcout));
	adder i1 (.in1(pcout), .in2(4'b0001), .out(nxtadrs));
    selector i2 (.in1(nxtadrs), .in2(jumpadrs), .sel(isjump), .out(selout));
	rom i3 (.ad(pcout), .do(inst));

endmodule

src/main/testfetch.v
`timescale 1ps/1ps
`include "fetch.v"

module test_fetch;

    reg rst, clk, isjump;
    reg[3:0] jumpadrs;
	wire[7:0]inst;
		       
	fetch i0 (.rst(rst), .clk(clk), .jumpadrs(jumpadrs), .isjump(isjump), .inst(inst));
					  
	initial begin
	/* #100は100psだけ時間経過させる、と解釈する */		
	    rst = 1'b0;  clk = 1'b0;    isjump = 1'b0;
	    #100    rst=1'b1;    clk = 1'b1;
	    #100    clk = 1'b0;
        #100    clk = 1'b1;
	    #100    clk = 1'b0;
        #100    clk = 1'b1;
	    #100    clk = 1'b0;
        #100    clk = 1'b1;
	    #100    clk = 1'b0;
        #100    clk = 1'b1;
	    #100    clk = 1'b0;
        #100    clk = 1'b1;
	    #100    clk = 1'b0;
        #100    clk = 1'b1;
	    #100    clk = 1'b0;
	    $finish(0);
    end


	initial begin
	   
	   /* 結果出力:%記号と後ろの配線名の並びは、C言語のprintfのような対応をしている */
	   /* 機械採点の都合上、ここは書き換えないように */
        $monitor($time, , "clk = %b  inst = %h  ", clk,inst);
        $dumpfile("output.vcd"); /*出力ファイル名,vcd形式で好きに付ける*/
        $dumpvars(0,test_fetch);
           /* GTKwaveで表示するための記述があればここに書くがまだしない */
           /* 知っている人は書いてもよいが、「提出時にはコメントアウトしておくこと」 */
           
        end
endmodule

src/main/output.vcd
$date
	Tue Sep 28 16:00:33 2021
$end
$version
	Icarus Verilog
$end
$timescale
	1ps
$end
$scope module test_fetch $end
$var wire 8 ! inst [7:0] $end
$var reg 1 " clk $end
$var reg 1 # isjump $end
$var reg 4 $ jumpadrs [3:0] $end
$var reg 1 % rst $end
$scope module i0 $end
$var wire 1 " clk $end
$var wire 1 # isjump $end
$var wire 4 & jumpadrs [3:0] $end
$var wire 1 % rst $end
$var wire 4 ' selout [3:0] $end
$var wire 4 ( pcout [3:0] $end
$var wire 4 ) nxtadrs [3:0] $end
$var wire 8 * inst [7:0] $end
$scope module i0 $end
$var wire 1 " clk $end
$var wire 1 % rst $end
$var wire 4 + in [3:0] $end
$var reg 4 , out [3:0] $end
$upscope $end
$scope module i1 $end
$var wire 4 - in1 [3:0] $end
$var wire 4 . in2 [3:0] $end
$var reg 4 / out [3:0] $end
$upscope $end
$scope module i2 $end
$var wire 4 0 in1 [3:0] $end
$var wire 4 1 in2 [3:0] $end
$var wire 1 # sel $end
$var reg 4 2 out [3:0] $end
$upscope $end
$scope module i3 $end
$var wire 4 3 ad [3:0] $end
$var reg 8 4 do [7:0] $end
$upscope $end
$upscope $end
$upscope $end
$enddefinitions $end
#0
$dumpvars
bx 4
b0 3
b1 2
bx 1
b1 0
b1 /
b1 .
b0 -
b0 ,
b1 +
bx *
b1 )
b0 (
b1 '
bx &
0%
bx $
0#
0"
bx !
$end
#1
b1010 !
b1010 *
b1010 4
#100
b10 '
b10 +
b10 2
b10 )
b10 /
b10 0
b1 (
b1 ,
b1 -
b1 3
1"
1%
#101
b1010001 !
b1010001 *
b1010001 4
#200
0"
#300
b11 '
b11 +
b11 2
b11 )
b11 /
b11 0
b10 (
b10 ,
b10 -
b10 3
1"
#301
b110000 !
b110000 *
b110000 4
#400
0"
#500
b100 '
b100 +
b100 2
b100 )
b100 /
b100 0
b11 (
b11 ,
b11 -
b11 3
1"
#501
b1110000 !
b1110000 *
b1110000 4
#600
0"
#700
b101 '
b101 +
b101 2
b101 )
b101 /
b101 0
b100 (
b100 ,
b100 -
b100 3
1"
#701
b10101 !
b10101 *
b10101 4
#800
0"
#900
b110 '
b110 +
b110 2
b110 )
b110 /
b110 0
b101 (
b101 ,
b101 -
b101 3
1"
#901
b1000111 !
b1000111 *
b1000111 4
#1000
0"
#1100
b111 '
b111 +
b111 2
b111 )
b111 /
b111 0
b110 (
b110 ,
b110 -
b110 3
1"
#1101
b11111111 !
b11111111 *
b11111111 4
#1200
0"
#1300
b1000 '
b1000 +
b1000 2
b1000 )
b1000 /
b1000 0
b111 (
b111 ,
b111 -
b111 3
1"
#1301
b0 !
b0 *
b0 4
